<?xml version="1.0" encoding="UTF-8" ?>
<suite name="suitename">
    <test name="RunAll">
        <classes>
            <class name="com.course.testng.groups.GroupsOnClass1"></class>
            <class name="com.course.testng.groups.GroupsOnClass2"></class>
            <class name="com.course.testng.groups.GroupsOnClass3"></class>
        </classes>
    </test>
    <test name="OnlyRunStu">
        <groups>
            <run>
                <include name="stu"/>
            </run>
        </groups>
        <classes>
            <class name="com.course.testng.groups.GroupsOnClass1"></class>
            <class name="com.course.testng.groups.GroupsOnClass2"></class>
            <class name="com.course.testng.groups.GroupsOnClass3"></class>
        </classes>
    </test>
</suite>